daleydai/__init__.py
daleydai/app.py
daleydai/constants.py
daleydai/scraper.py
daleydai/ss.py
daleydai/utils.py
daleydai/commands/__init__.py
daleydai/commands/broker.py
daleydai/commands/buyer.py
daleydai/commands/mero.py
daleydai/commands/meroshares.py
daleydai/commands/seller.py
daleydai-0.0.3.dist-info/METADATA
daleydai-0.0.3.dist-info/WHEEL
daleydai-0.0.3.dist-info/entry_points.txt
daleydai-0.0.3.dist-info/top_level.txt
daleydai-0.0.3.dist-info/RECORD
