Metadata-Version: 2.1
Name: daleydai
Version: 0.0.3
Summary: karod bata road...
Home-page: https://github.com/sumansta/daleydai
Author: Suman Shrestha
License: MIT
Platform: UNKNOWN
Classifier: Programming Language :: Python :: 3.6
Classifier: Programming Language :: Python :: 3.7
Classifier: Programming Language :: Python :: 3.8
Classifier: Operating System :: OS Independent
Classifier: License :: OSI Approved :: MIT License
Requires-Dist: requests
Requires-Dist: pandas
Requires-Dist: click
Requires-Dist: rich
